{"spawners":{"spawner_0":{"pattern":["spawner_1","spawner_4"],"patternTime":"3","patternRepeat":"4"},"spawner_1":{"pattern":["spawner_5","wait"],"patternTime":"3","patternRepeat":"0"},"spawner_2":{"pattern":["bullet","bullet","bullet"],"patternTime":"6","patternRepeat":"2","spawnerPhase":"180","spawnerRadius":"15, 50, 4, 5, circle","spawnedNumber":"2, 4, -0.5, 6, reverse","spawnedAngle":"140","spawnedSpeed":"3, 5, -0.6, 5, reverse","bulletRadius":"14, 28, 4, 3, circle"},"spawner_3":{"pattern":["spawner_0"],"patternTime":"2","patternRepeat":"4","spawnerPhase":"40, 300, -5, 5, circle","spawnerRadius":"60"},"spawner_4":{"pattern":["spawner_5","wait"],"patternTime":"2","patternRepeat":"0","spawnerPhase":"160, 350, -4, 5, reverse","spawnerRadius":"60"},"spawner_5":{"pattern":["bullet","wait"],"patternTime":"3","patternRepeat":"2","spawnerPhase":"60, 220, 1, 2, circle","spawnerRadius":"20, 25, 4, 3, circle"},"spawner_6":{"pattern":["spawner_0"],"patternTime":"5","patternRepeat":"1"},"spawner_7":{"pattern":["bullet"],"patternTime":"2","patternRepeat":"0","spawnerPhase":"0","spawnerRadius":"60","spawnedNumber":"3, 5, -0.5, 4, circle","spawnedAngle":"110","spawnedSpeed":"4","bulletRadius":"10"},"spawner_8":{"pattern":["bullet","bullet"],"patternTime":"3","patternRepeat":"2"},"spawner_9":{"pattern":["bullet"],"patternTime":"3","patternRepeat":"0"}},"boss":{"script":[{"health":"1","events":["clear, spawner_3"]},{"health":"0.9","events":["spawn, spawner_6","clear, spawner_4","spawn, spawner_5, 80, 90"]},{"health":"0.8","events":["spawn, spawner_0"]},{"health":"0.7","events":["spawn, spawner_2, 0, 310"]},{"health":"0.6","events":["spawn, spawner_6","clear, spawner_4"]},{"health":"0.5","events":["spawn, spawner_8"]},{"health":"0.4","events":["spawn, spawner_0","spawn, spawner_4"]},{"health":"0.3","events":["spawn, spawner_5, 0, 250, 2, 240"]},{"health":"0.2","events":["spawn, spawner_5","spawn, spawner_9, 40, 160, 4, 140"]},{"health":"0.1","events":["spawn, spawner_2, 0, 310"]}]}}